bcg_analysis
