Metadata-Version: 1.0
Name: bcganalysis
Version: 1.0.0
Summary: Builds BCG Matrix
Home-page: https://github.com/mateil04/bcg_analysis
Author: Matias Eiletz
Author-email: mat.eil1991@gmail.com
License: UNKNOWN
Keywords: BCG Growth Share Matrix Feature Importance Clustering
Platform: UNKNOWN
